WebCore-2.0.4-py3.8-nspkg.pth
web/app/static.py
web/app/__pycache__/static.cpython-38.opt-1.pyc
web/core/__init__.py
web/core/application.py
web/core/compat.py
web/core/context.py
web/core/dispatch.py
web/core/extension.py
web/core/release.py
web/core/util.py
web/core/view.py
web/core/__pycache__/__init__.cpython-38.opt-1.pyc
web/core/__pycache__/application.cpython-38.opt-1.pyc
web/core/__pycache__/compat.cpython-38.opt-1.pyc
web/core/__pycache__/context.cpython-38.opt-1.pyc
web/core/__pycache__/dispatch.cpython-38.opt-1.pyc
web/core/__pycache__/extension.cpython-38.opt-1.pyc
web/core/__pycache__/release.cpython-38.opt-1.pyc
web/core/__pycache__/util.cpython-38.opt-1.pyc
web/core/__pycache__/view.cpython-38.opt-1.pyc
web/ext/acl.py
web/ext/analytics.py
web/ext/annotation.py
web/ext/args.py
web/ext/base.py
web/ext/debug.py
web/ext/local.py
web/ext/serialize.py
web/ext/__pycache__/acl.cpython-38.opt-1.pyc
web/ext/__pycache__/analytics.cpython-38.opt-1.pyc
web/ext/__pycache__/annotation.cpython-38.opt-1.pyc
web/ext/__pycache__/args.cpython-38.opt-1.pyc
web/ext/__pycache__/base.cpython-38.opt-1.pyc
web/ext/__pycache__/debug.cpython-38.opt-1.pyc
web/ext/__pycache__/local.cpython-38.opt-1.pyc
web/ext/__pycache__/serialize.cpython-38.opt-1.pyc
web/server/appengine.py
web/server/cherrypy_.py
web/server/diesel_.py
web/server/eventlet_.py
web/server/fcgi.py
web/server/gevent_.py
web/server/stdlib.py
web/server/tornado_.py
web/server/waitress_.py
web/server/__pycache__/appengine.cpython-38.opt-1.pyc
web/server/__pycache__/cherrypy_.cpython-38.opt-1.pyc
web/server/__pycache__/diesel_.cpython-38.opt-1.pyc
web/server/__pycache__/eventlet_.cpython-38.opt-1.pyc
web/server/__pycache__/fcgi.cpython-38.opt-1.pyc
web/server/__pycache__/gevent_.cpython-38.opt-1.pyc
web/server/__pycache__/stdlib.cpython-38.opt-1.pyc
web/server/__pycache__/tornado_.cpython-38.opt-1.pyc
web/server/__pycache__/waitress_.cpython-38.opt-1.pyc
WebCore-2.0.4.dist-info/LICENSE.txt
WebCore-2.0.4.dist-info/METADATA
WebCore-2.0.4.dist-info/WHEEL
WebCore-2.0.4.dist-info/entry_points.txt
WebCore-2.0.4.dist-info/namespace_packages.txt
WebCore-2.0.4.dist-info/top_level.txt
WebCore-2.0.4.dist-info/zip-safe
WebCore-2.0.4.dist-info/RECORD
