Metadata-Version: 2.1
Name: WebCore
Version: 2.0.4
Summary: A powerful web development nanoframework so small it's not even a microframework.
Home-page: https://github.com/marrow/WebCore/
Author: Alice Bevan-McGregor
Author-email: alice@gothcandy.com
License: MIT
Download-URL: https://github.com/marrow/WebCore/releases
Keywords: marrow,web.core,web.ext
Platform: UNKNOWN
Classifier: Development Status :: 5 - Production/Stable
Classifier: Environment :: Console
Classifier: Environment :: Web Environment
Classifier: Intended Audience :: Developers
Classifier: License :: OSI Approved :: MIT License
Classifier: Operating System :: OS Independent
Classifier: Programming Language :: Python
Classifier: Programming Language :: Python :: 2
Classifier: Programming Language :: Python :: 2.7
Classifier: Programming Language :: Python :: 3
Classifier: Programming Language :: Python :: 3.2
Classifier: Programming Language :: Python :: 3.3
Classifier: Programming Language :: Python :: 3.4
Classifier: Programming Language :: Python :: 3.5
Classifier: Programming Language :: Python :: Implementation :: CPython
Classifier: Programming Language :: Python :: Implementation :: PyPy
Classifier: Topic :: Internet :: WWW/HTTP :: Dynamic Content
Classifier: Topic :: Internet :: WWW/HTTP :: WSGI
Classifier: Topic :: Software Development :: Libraries
Classifier: Topic :: Software Development :: Libraries :: Application Frameworks
Classifier: Topic :: Software Development :: Libraries :: Python Modules
Requires-Dist: marrow.package (<2.0)
Requires-Dist: WebOb
Requires-Dist: pathlib2 ; python_version < "3.4"
Provides-Extra: asset
Requires-Dist: webassets ; extra == 'asset'
Provides-Extra: bjoern
Requires-Dist: bjoern ; extra == 'bjoern'
Provides-Extra: bson
Requires-Dist: pymongo ; extra == 'bson'
Provides-Extra: cherrypy
Requires-Dist: cherrypy ; extra == 'cherrypy'
Provides-Extra: cli
Requires-Dist: web.command ; extra == 'cli'
Provides-Extra: database
Requires-Dist: web.db ; extra == 'database'
Requires-Dist: pymongo ; extra == 'database'
Provides-Extra: development
Requires-Dist: pytest ; extra == 'development'
Requires-Dist: pytest-cov ; extra == 'development'
Requires-Dist: pytest-flakes ; extra == 'development'
Requires-Dist: pytest-capturelog ; extra == 'development'
Requires-Dist: web.dispatch.object ; extra == 'development'
Requires-Dist: backlash ; extra == 'development'
Requires-Dist: ptpython ; extra == 'development'
Requires-Dist: ipython ; extra == 'development'
Requires-Dist: pudb ; extra == 'development'
Requires-Dist: waitress ; extra == 'development'
Provides-Extra: diesel
Requires-Dist: diesel ; extra == 'diesel'
Provides-Extra: eventlet
Requires-Dist: eventlet ; extra == 'eventlet'
Provides-Extra: flup
Requires-Dist: flup6 ; extra == 'flup'
Provides-Extra: gevent
Requires-Dist: gevent ; extra == 'gevent'
Provides-Extra: object
Requires-Dist: web.dispatch.object ; extra == 'object'
Provides-Extra: paste
Requires-Dist: paste ; extra == 'paste'
Provides-Extra: production
Requires-Dist: flup6 ; extra == 'production'
Provides-Extra: route
Requires-Dist: web.dispatch.route ; extra == 'route'
Provides-Extra: template
Requires-Dist: web.template ; extra == 'template'
Requires-Dist: cinje ; extra == 'template'
Provides-Extra: tornado
Requires-Dist: tornado ; extra == 'tornado'
Provides-Extra: traversal
Requires-Dist: web.dispatch.traversal ; extra == 'traversal'
Provides-Extra: waitress
Requires-Dist: waitress ; extra == 'waitress'
Provides-Extra: yaml
Requires-Dist: pyyaml ; extra == 'yaml'
